better_fasta_grep/__init__.py
better_fasta_grep/bfg.py
better_fasta_grep-1.0.2.dist-info/LICENSE
better_fasta_grep-1.0.2.dist-info/METADATA
better_fasta_grep-1.0.2.dist-info/WHEEL
better_fasta_grep-1.0.2.dist-info/entry_points.txt
better_fasta_grep-1.0.2.dist-info/top_level.txt
better_fasta_grep-1.0.2.dist-info/RECORD
