Metadata-Version: 2.1
Name: better-fasta-grep
Version: 1.0.2
Summary: Grep-like tool for retrieving matching sequence records from a FASTA file
Home-page: https://github.com/fethalen/better_fasta_grep
Author: Felix Thalen, Clemens Mauksch
Author-email: felix.thalen@uni-goettingen.de, clemens.mauksch@uni-goettingen.de
License: GPL 3
Keywords: bioinformatics,fasta,grep,regular-expressions,bioinformatics-tool,grep-like
Platform: UNKNOWN
Classifier: Programming Language :: Python :: 3
Classifier: License :: OSI Approved :: GNU General Public License v3 (GPLv3)
Classifier: Operating System :: OS Independent
Classifier: Topic :: Scientific/Engineering :: Bio-Informatics
Requires-Python: >=3.6
License-File: LICENSE
Requires-Dist: setuptools (>=30.3.0wheelsetuptools_scm)
